pyhomotopy/StefanSolver.py
pyhomotopy/__init__.py
pyhomotopy/algebraicEqSolver.py
pyhomotopy/deformationEquations.py
pyhomotopy/geometry.py
pyhomotopy/hamBase.py
pyhomotopy/hamBcs.py
pyhomotopy/hamCommons.py
pyhomotopy/hamErrors.py
pyhomotopy/hamExtTest.py
pyhomotopy/hamManager.py
pyhomotopy/hamParser.py
pyhomotopy/hamPlotter.py
pyhomotopy/hamResult.py
pyhomotopy/hamSolver.py
pyhomotopy/hamSymbols.py
pyhomotopy/hamTask.py
pyhomotopy/hamUI.py
pyhomotopy/main.py
pyhomotopy/odeSolver.py
pyhomotopy/pdeSolver.py
pyhomotopy/quickDbg.py
pyhomotopy-0.0.1.dist-info/LICENSE
pyhomotopy-0.0.1.dist-info/METADATA
pyhomotopy-0.0.1.dist-info/WHEEL
pyhomotopy-0.0.1.dist-info/top_level.txt
pyhomotopy-0.0.1.dist-info/RECORD
