Metadata-Version: 2.1
Name: pyhomotopy
Version: 0.0.1
Summary: A package to solve nonlinear equations with HAM
Home-page: https://github.com/polyneikis11/pyHAM
Author: Polyneikis Strongylis
Author-email: polyneikis11@gmail.com
License: UNKNOWN
Platform: UNKNOWN
Classifier: Programming Language :: Python :: 3
Classifier: License :: OSI Approved :: MIT License
Classifier: Operating System :: OS Independent
Requires-Python: >=3.6
